smores/__init__.py
smores/psi4.py
smores/py.typed
smores/xtb.py
smores/_internal/__init__.py
smores/_internal/combine.py
smores/_internal/constants.py
smores/_internal/esp_molecule.py
smores/_internal/molecule.py
smores/_internal/psi4.py
smores/_internal/steric_parameters.py
smores/_internal/utilities.py
smores/_internal/voxel_grid.py
smores/_internal/write_cube.py
smores/_internal/xtb.py
chem_smores-0.0.0.dist-info/LICENSE
chem_smores-0.0.0.dist-info/METADATA
chem_smores-0.0.0.dist-info/WHEEL
chem_smores-0.0.0.dist-info/top_level.txt
chem_smores-0.0.0.dist-info/RECORD
